Metadata-Version: 2.4
Name: pyThermoModels
Version: 1.6.0
Summary: PyThermoModels is an open-source Python package designed to facilitate thermodynamic modeling and calculations. This package provides a comprehensive and user-friendly interface to popular thermodynamic models, enabling quick and accurate estimation of key properties.
Home-page: https://github.com/sinagilassi/PyThermoModels
Author: Sina Gilassi
Author-email: Sina Gilassi <sina.gilassi@gmail.com>
License-Expression: MIT
Project-URL: Homepage, https://github.com/sinagilassi/PyThermoModels
Project-URL: Documentation, https://pythermomodels.readthedocs.io/en/latest/
Project-URL: Source, https://github.com/sinagilassi/PyThermoModels
Project-URL: Tracker, https://github.com/sinagilassi/PyThermoModels/issues
Keywords: chemical-engineering,equation-of-state,thermodynamic-properties,activity-coefficient,thermodynamic-models,NRTL,UNIQUAC,SRK,PR,RK,vdW
Classifier: Development Status :: 1 - Planning
Classifier: Intended Audience :: Education
Classifier: Programming Language :: Python :: 3.11
Classifier: Operating System :: Unix
Classifier: Operating System :: MacOS :: MacOS X
Classifier: Operating System :: Microsoft :: Windows
Requires-Python: >=3.10
License-File: LICENSE
Requires-Dist: numpy>=2.3.3
Requires-Dist: scipy>=1.16.2
Requires-Dist: pydantic-settings>=2.10.1
Requires-Dist: pydantic>=2.11.9
Requires-Dist: pyyaml>=6.0.2
Requires-Dist: pythermodb
Requires-Dist: pythermodb-settings
Requires-Dist: pythermolinkdb
Requires-Dist: pycuc
Dynamic: author
Dynamic: home-page
Dynamic: license-file
Dynamic: requires-python
